{
    "Name": "Miscellaneous system checks",
    "Checklist" : [
        {
            "Name": "CPU temperature threshold",
            "ID": "temp",
            "Parameters": ["80"]
        },
        {
            "Name": "/sbin/init check",
            "ID" : "running",
            "Parameters": ["/sbin/init"]
        },
        {
            "ID" : "module",
            "Parameters" : ["ext4"]
        },
        {
            "ID" : "kernelParameter",
            "Parameters" : ["kernel.ctrl-alt-del"]
        },
        {
            "ID" : "phpConfig",
            "Parameters" : ["default_mimetype", "text/html"]
        },
        {
            "ID" : "command",
            "Parameters" : ["sleep .00001"]
        },
        {
            "ID" : "commandOutputMatches",
            "Parameters" : ["echo works", "\\w[aeiou]+(y) r[kl]s"]
        }
    ]
}
