{
    "Name": "Miscellanious system checks, designed to fail",
    "Checklist" : [
        {
            "Name": "CPU temperature threshold",
            "Check": "temp",
            "Parameters": ["10"]
        },
        {
            "Name": "failing process check",
            "Check" : "running",
            "Parameters": ["failme"]
        },
        {
            "Notes": "Example of a check that will report an error",
            "Check" : "command",
            "Parameters" : ["failme"]
        },
        {
            "Check" : "module",
            "Parameters" : ["failme"]
        },
        {
            "Check" : "kernelParameter",
            "Parameters" : ["failme"]
        },
        {
            "Check" : "phpConfig",
            "Parameters" : ["default_mimetype", "failme"]
        }
    ]
}
